rmqworkers/__init__.py
rmqworkers/connection.py
rmqworkers/errors.py
rmqworkers/logs.py
rmqworkers/queues.py
rmqworkers/rmqWorker.py
rmqworkers/examples/__init__.py
rmqworkers/examples/example_1queue_in.py
rmqworkers/examples/example_1queue_in_and_1queue_out.py
rmqworkers/examples/example_1queue_in_and_1queue_out_process.py
rmqworkers-0.0.4.dist-info/LICENCE
rmqworkers-0.0.4.dist-info/METADATA
rmqworkers-0.0.4.dist-info/WHEEL
rmqworkers-0.0.4.dist-info/top_level.txt
rmqworkers-0.0.4.dist-info/RECORD
