Metadata-Version: 2.1
Name: rmqworkers
Version: 0.0.4
Summary: Rabbit MQ wrapper implement with amqpstorm and with threading or multiprocessing
Home-page: https://github.com/popescu-catalin-ionut/rmqworkers
Author: Popescu Catalin-Ionut
Author-email: popescu.catalin.ionut@gmail.com
License: Apache License 2.0
Keywords: rabbitmq,amqpstorm,amqp
Platform: any
Classifier: Programming Language :: Python :: 3
Classifier: License :: OSI Approved :: MIT License
Classifier: Operating System :: OS Independent
Classifier: Development Status :: 5 - Production/Stable
Classifier: Topic :: System :: Networking
Classifier: Natural Language :: English
Requires-Python: >=3.6
